userinfo/__init__.py
userinfo-1.0.0.dist-info/METADATA
userinfo-1.0.0.dist-info/WHEEL
userinfo-1.0.0.dist-info/top_level.txt
userinfo-1.0.0.dist-info/RECORD
