Metadata-Version: 2.1
Name: userinfo
Version: 1.0.0
Summary: Get placeholder user information on python3!
Home-page: https://github.com/voxj/userinfo/
Author: voxj.
